opredflag/__init__.py
opredflag/cli.py
opredflag/py.typed
opredflag/updater/__init__.py
opredflag/updater/cli.py
opredflag/updater/core.py
opredflag/updater/enums.py
opredflag-0.3.0.dist-info/LICENSE
opredflag-0.3.0.dist-info/METADATA
opredflag-0.3.0.dist-info/WHEEL
opredflag-0.3.0.dist-info/entry_points.txt
opredflag-0.3.0.dist-info/top_level.txt
opredflag-0.3.0.dist-info/RECORD
