Metadata-Version: 2.1
Name: opredflag
Version: 0.3.0
Summary: A script which automatically updates OPRF standard asset files from the OpRedFlag repository
Author: BobDotCom
Project-URL: Homepage, https://github.com/BobDotCom/py-opredflag
Project-URL: Repository, https://github.com/BobDotCom/py-opredflag
Project-URL: Documentation, https://opredflag.readthedocs.io
Project-URL: Changelog, https://github.com/BobDotCom/py-opredflag/blob/main/CHANGELOG.md
Project-URL: Tracker, https://github.com/BobDotCom/py-opredflag/issues
Classifier: Development Status :: 2 - Pre-Alpha
Classifier: Intended Audience :: Developers
Classifier: Natural Language :: English
Classifier: Operating System :: OS Independent
Classifier: Programming Language :: Python :: 3.10
Classifier: Programming Language :: Python :: 3.11
Classifier: Programming Language :: Python :: 3.12
Classifier: Topic :: Software Development :: Libraries
Classifier: Topic :: Software Development :: Libraries :: Python Modules
Classifier: Topic :: Utilities
Classifier: Typing :: Typed
Classifier: License :: OSI Approved :: GNU General Public License v3 (GPLv3)
Requires-Python: >=3.10
License-File: LICENSE
Requires-Dist: aiohttp ==3.10.10
Requires-Dist: async-lru ==2.0.4
Requires-Dist: semver ==3.0.2
Requires-Dist: typing-extensions ~=4.0 ; python_version < "3.11"
Provides-Extra: docs
Requires-Dist: sphinx ==8.1.3 ; extra == 'docs'
Requires-Dist: sphinxcontrib-trio ==1.1.2 ; extra == 'docs'
Requires-Dist: sphinxcontrib-websupport ==2.0.0 ; extra == 'docs'
Requires-Dist: myst-parser ==4.0.0 ; extra == 'docs'
Requires-Dist: sphinxext-opengraph ==0.9.1 ; extra == 'docs'
Requires-Dist: sphinx-copybutton ==0.5.2 ; extra == 'docs'
Requires-Dist: furo ==2024.8.6 ; extra == 'docs'
Requires-Dist: sphinx-autodoc-typehints ==2.5.0 ; extra == 'docs'
Requires-Dist: sphinx-argparse ==0.5.2 ; extra == 'docs'
Provides-Extra: speedups
Requires-Dist: aiohttp[speedups] ; extra == 'speedups'
